{
  "enemies": {
    "goblin": {
      "name": "Goblin",
      "stats": {
        "hp": 4,
        "atk": 1,
        "def": 1,
        "agi": 1
      },
      "movementSpeed": 1,
      "aiType": "Hunter",
      "sprite": "goblin",
      "flying": false,
      "tier": 1,
      "dropChance": 0.1
    },
    "bat": {
      "name": "Bat",
      "stats": {
        "hp": 4,
        "atk": 1,
        "def": 1,
        "agi": 1
      },
      "movementSpeed": 2,
      "aiType": "Hunter",
      "sprite": "bat",
      "flying": true,
      "tier": 1,
      "dropChance": 0.1
    },
    "archer": {
      "name": "Archer",
      "stats": {
        "hp": 3,
        "atk": 2,
        "def": 0,
        "agi": 2
      },
      "movementSpeed": 1,
      "aiType": "Ranged",
      "sprite": "archer",
      "flying": false,
      "tier": 1,
      "dropChance": 0.15,
      "projectile": "arrow"
    },
    "brute": {
      "name": "Brute",
      "stats": {
        "hp": 8,
        "atk": 3,
        "def": 2,
        "agi": 0
      },
      "movementSpeed": 0.5,
      "aiType": "Hunter",
      "sprite": "brute",
      "flying": false,
      "tier": 2,
      "dropChance": 0.2
    },
    "shaman": {
      "name": "Shaman",
      "stats": {
        "hp": 4,
        "atk": 1,
        "def": 1,
        "agi": 1
      },
      "movementSpeed": 1,
      "aiType": "Healer",
      "sprite": "shaman",
      "flying": false,
      "tier": 2,
      "dropChance": 0.2
    },
    "assassin": {
      "name": "Assassin",
      "stats": {
        "hp": 5,
        "atk": 3,
        "def": 0,
        "agi": 3
      },
      "movementSpeed": 1,
      "aiType": "Teleporter",
      "sprite": "assassin",
      "flying": false,
      "tier": 3,
      "dropChance": 0.25
    },
    "skeleton": {
      "name": "Skeleton",
      "stats": {
        "hp": 3,
        "atk": 2,
        "def": 0,
        "agi": 1
      },
      "movementSpeed": 1,
      "aiType": "Hunter",
      "sprite": "skeleton",
      "flying": false,
      "tier": 1,
      "dropChance": 0.05
    },
    "summoner": {
      "name": "Summoner",
      "stats": {
        "hp": 6,
        "atk": 1,
        "def": 1,
        "agi": 2
      },
      "movementSpeed": 1,
      "aiType": "Summoner",
      "sprite": "summoner",
      "flying": false,
      "tier": 3,
      "dropChance": 0.3
    }
  },
  "player": {
    "name": "Player",
    "stats": {
      "hp": 10,
      "atk": 3,
      "def": 1,
      "agi": 2
    },
    "flying": false
  }
}
